{
	"bmi-installation" : null,
	"compiler-frontend-variant" : "MSVC",
	"compiler-id" : "MSVC",
	"compiler-simulate-id" : "",
	"config" : "Debug",
	"cxx-modules" : {},
	"database-info" : null,
	"dir-cur-bld" : "D:/path_plan/cmake-build-debug",
	"dir-cur-src" : "D:/path_plan",
	"dir-top-bld" : "D:/path_plan/cmake-build-debug",
	"dir-top-src" : "D:/path_plan",
	"exports" : [],
	"forward-modules-from-target-dirs" : [],
	"include-dirs" : 
	[
		"D:\\path_plan\\include"
	],
	"language" : "CXX",
	"linked-target-dirs" : [],
	"module-dir" : "D:/path_plan/cmake-build-debug/CMakeFiles/path_plan.dir",
	"sources" : 
	{
		"CMakeFiles/path_plan.dir/src/AStar.cpp.obj" : 
		{
			"language" : "CXX",
			"source" : "D:/path_plan/src/AStar.cpp"
		},
		"CMakeFiles/path_plan.dir/src/AdjMatrixGraph.cpp.obj" : 
		{
			"language" : "CXX",
			"source" : "D:/path_plan/src/AdjMatrixGraph.cpp"
		},
		"CMakeFiles/path_plan.dir/src/CBS.cpp.obj" : 
		{
			"language" : "CXX",
			"source" : "D:/path_plan/src/CBS.cpp"
		},
		"CMakeFiles/path_plan.dir/src/DirectedGraph.cpp.obj" : 
		{
			"language" : "CXX",
			"source" : "D:/path_plan/src/DirectedGraph.cpp"
		},
		"CMakeFiles/path_plan.dir/src/Grid.cpp.obj" : 
		{
			"language" : "CXX",
			"source" : "D:/path_plan/src/Grid.cpp"
		},
		"CMakeFiles/path_plan.dir/src/sipp.cpp.obj" : 
		{
			"language" : "CXX",
			"source" : "D:/path_plan/src/sipp.cpp"
		},
		"CMakeFiles/path_plan.dir/test/auto_ptr1.cpp.obj" : 
		{
			"language" : "CXX",
			"source" : "D:/path_plan/test/auto_ptr1.cpp"
		},
		"CMakeFiles/path_plan.dir/test/recur.cpp.obj" : 
		{
			"language" : "CXX",
			"source" : "D:/path_plan/test/recur.cpp"
		},
		"CMakeFiles/path_plan.dir/test/sort.cpp.obj" : 
		{
			"language" : "CXX",
			"source" : "D:/path_plan/test/sort.cpp"
		},
		"CMakeFiles/path_plan.dir/test/testAStarSimpleLinePath.cpp.obj" : 
		{
			"language" : "CXX",
			"source" : "D:/path_plan/test/testAStarSimpleLinePath.cpp"
		},
		"CMakeFiles/path_plan.dir/test/testAdjMatrixGraph.cpp.obj" : 
		{
			"language" : "CXX",
			"source" : "D:/path_plan/test/testAdjMatrixGraph.cpp"
		},
		"CMakeFiles/path_plan.dir/test/testCBSSimpleLinePath.cpp.obj" : 
		{
			"language" : "CXX",
			"source" : "D:/path_plan/test/testCBSSimpleLinePath.cpp"
		},
		"CMakeFiles/path_plan.dir/test/testSippSimpleLinePath.cpp.obj" : 
		{
			"language" : "CXX",
			"source" : "D:/path_plan/test/testSippSimpleLinePath.cpp"
		}
	}
}